lernsax/__init__.py
lernsax/lernsax.py
lernsax/util/__init__.py
lernsax/util/client.py
lernsax/util/exceptions.py
lernsax-1.5.3.dist-info/LICENSE
lernsax-1.5.3.dist-info/METADATA
lernsax-1.5.3.dist-info/WHEEL
lernsax-1.5.3.dist-info/top_level.txt
lernsax-1.5.3.dist-info/RECORD
