Metadata-Version: 2.1
Name: lernsax
Version: 1.5.3
Summary: A Python Async LernSax Client
Home-page: https://github.com/okok7711/lernsax
Author: okok7711
Author-email: okok7711@etstun.de
License: MIT License
Keywords: lernsax,client,files,internet,download,upload,sachsen,deutschland,ostdeutschland
Platform: UNKNOWN
Classifier: Intended Audience :: Developers
Classifier: License :: OSI Approved :: MIT License
Classifier: Operating System :: OS Independent
Classifier: Programming Language :: Python
Classifier: Programming Language :: Python :: 3.5
Classifier: Programming Language :: Python :: 3.6
Classifier: Programming Language :: Python :: 3.7
Classifier: Programming Language :: Python :: 3.8
Classifier: Programming Language :: Python :: 3.9
Classifier: Programming Language :: Python :: 3.10
License-File: LICENSE
Requires-Dist: python-box
Requires-Dist: aiohttp
Requires-Dist: aiodav
